cryptolibrary
