Metadata-Version: 2.1
Name: cryptolibrary
Version: 0.0.4
Summary: Cryptography libary
Home-page: 
Author: Enzo Quental
Author-email: ezq2202@gmail.com
License: MIT
Keywords: crypto
Classifier: Development Status :: 5 - Production/Stable
Classifier: Intended Audience :: Education
Classifier: Operating System :: Microsoft :: Windows :: Windows 10
Classifier: License :: OSI Approved :: MIT License
Classifier: Programming Language :: Python :: 3
License-File: LICENSE.txt
